payoffgraph-juttu.py
payoffgraph_juttu.py
payoffgraph_juttu-0.1.0.dist-info/LICENSE
payoffgraph_juttu-0.1.0.dist-info/METADATA
payoffgraph_juttu-0.1.0.dist-info/WHEEL
payoffgraph_juttu-0.1.0.dist-info/top_level.txt
payoffgraph_juttu-0.1.0.dist-info/RECORD
