Metadata-Version: 2.1
Name: payoffgraph-juttu
Version: 0.1.0
Summary: Get the most beautiful Payoff Chart using a single simple function
Home-page: https://github.com/Juttu/ss
Author: Juttu G Anurag
License: UNKNOWN
Keywords: payoff graph,options,opstra,sensibull
Platform: UNKNOWN
Classifier: Programming Language :: Python :: 3
Classifier: License :: OSI Approved :: MIT License
Classifier: Operating System :: OS Independent
Requires-Python: >=3.6
License-File: LICENSE
Requires-Dist: numpy
Requires-Dist: pandas
Requires-Dist: streamlit
Requires-Dist: plotly
Requires-Dist: typing (>=3.7.4)
